marutils/__init__.py
marutils/georef.py
marutils/io.py
marutils/masking.py
marutils/xhourly.py
marutils-1.0.0.dist-info/LICENSE
marutils-1.0.0.dist-info/METADATA
marutils-1.0.0.dist-info/WHEEL
marutils-1.0.0.dist-info/top_level.txt
marutils-1.0.0.dist-info/RECORD
