Metadata-Version: 2.1
Name: marutils
Version: 1.0.0
Summary: Utilities and tools for working with MAR regional climate model outputs through xarray
Home-page: https://github.com/GlacioHack/marutils
Author: GlacioHack / Andrew Tedstone (@atedstone)
Author-email: andrew.tedstone@unifr.ch
License: UNKNOWN
Project-URL: Bug Tracker, https://github.com/GlacioHack/marutils/issues
Platform: UNKNOWN
Classifier: Programming Language :: Python :: 3
Classifier: License :: OSI Approved :: BSD License
Classifier: Operating System :: OS Independent
Requires-Python: >=3.6
